pyprof_timer/__about__.py
pyprof_timer/__info__.py
pyprof_timer/__init__.py
pyprof_timer/profiler.py
pyprof_timer/timer.py
pyprof_timer/tree.py
pyprof_timer/contrib/__init__.py
pyprof_timer/contrib/flask.py
pyprof_timer-0.0.7.dist-info/DESCRIPTION.rst
pyprof_timer-0.0.7.dist-info/METADATA
pyprof_timer-0.0.7.dist-info/RECORD
pyprof_timer-0.0.7.dist-info/WHEEL
pyprof_timer-0.0.7.dist-info/metadata.json
pyprof_timer-0.0.7.dist-info/top_level.txt
timer/__init__.py
timer/timer.py
timer/contrib/__init__.py
timer/contrib/flask.py
